{
  "header": {
    "save_format": 1,
    "name": "LIBERTY",
    "author": "",
    "level": 5,
    "hole": 7,
    "par": 3,
    "foreground": 5,
    "background": 2,
    "special": 2,
    "height": 620,
    "snap": 4,
    "n_static": 29,
    "n_elliptic": 0,
    "n_linear": 0
  },
  "body": {
    "StaticControl1": {
      "shape": 1,
      "x": 296,
      "y": 124,
      "angle": 0,
      "size": 0,
      "type": 2
    },
    "StaticControl2": {
      "shape": 2,
      "x": 60,
      "y": 80,
      "angle": -7,
      "size": 2,
      "type": 0
    },
    "StaticControl3": {
      "shape": 0,
      "x": 64,
      "y": 212,
      "angle": 84,
      "size": 1,
      "type": 0
    },
    "StaticControl4": {
      "shape": 0,
      "x": 60,
      "y": 136,
      "angle": 87,
      "size": 2,
      "type": 0
    },
    "StaticControl5": {
      "shape": 0,
      "x": 76,
      "y": 268,
      "angle": 74,
      "size": 1,
      "type": 0
    },
    "StaticControl6": {
      "shape": 0,
      "x": 60,
      "y": 340,
      "angle": 125,
      "size": 1,
      "type": 0
    },
    "StaticControl7": {
      "shape": 0,
      "x": 76,
      "y": 408,
      "angle": 118,
      "size": 1,
      "type": 0
    },
    "StaticControl8": {
      "shape": 0,
      "x": 108,
      "y": 356,
      "angle": 116,
      "size": 1,
      "type": 0
    },
    "StaticControl9": {
      "shape": 0,
      "x": 176,
      "y": 408,
      "angle": 149,
      "size": 1,
      "type": 0
    },
    "StaticControl10": {
      "shape": 0,
      "x": 124,
      "y": 444,
      "angle": 138,
      "size": 1,
      "type": 0
    },
    "StaticControl11": {
      "shape": 0,
      "x": 80,
      "y": 500,
      "angle": 116,
      "size": 1,
      "type": 0
    },
    "StaticControl12": {
      "shape": 0,
      "x": 196,
      "y": 464,
      "angle": 116,
      "size": 1,
      "type": 0
    },
    "StaticControl13": {
      "shape": 0,
      "x": 148,
      "y": 512,
      "angle": 117,
      "size": 1,
      "type": 0
    },
    "StaticControl14": {
      "shape": 0,
      "x": 104,
      "y": 584,
      "angle": 110,
      "size": 1,
      "type": 0
    },
    "StaticControl15": {
      "shape": 0,
      "x": 216,
      "y": 536,
      "angle": 88,
      "size": 1,
      "type": 0
    },
    "StaticControl16": {
      "shape": 0,
      "x": 168,
      "y": 572,
      "angle": 110,
      "size": 1,
      "type": 0
    },
    "StaticControl17": {
      "shape": 0,
      "x": 248,
      "y": 428,
      "angle": 51,
      "size": 1,
      "type": 0
    },
    "StaticControl18": {
      "shape": 0,
      "x": 264,
      "y": 488,
      "angle": 78,
      "size": 1,
      "type": 0
    },
    "StaticControl19": {
      "shape": 0,
      "x": 260,
      "y": 568,
      "angle": 78,
      "size": 1,
      "type": 0
    },
    "StaticControl20": {
      "shape": 0,
      "x": 324,
      "y": 504,
      "angle": 122,
      "size": 2,
      "type": 0
    },
    "StaticControl21": {
      "shape": 0,
      "x": 352,
      "y": 520,
      "angle": 122,
      "size": 2,
      "type": 0
    },
    "StaticControl22": {
      "shape": 0,
      "x": 312,
      "y": 548,
      "angle": 30,
      "size": 2,
      "type": 0
    },
    "StaticControl23": {
      "shape": 1,
      "x": 180,
      "y": 324,
      "angle": 116,
      "size": 2,
      "type": 1
    },
    "StaticControl24": {
      "shape": 2,
      "x": 180,
      "y": 268,
      "angle": 116,
      "size": 0,
      "type": 0
    },
    "StaticControl25": {
      "shape": 2,
      "x": 204,
      "y": 276,
      "angle": 163,
      "size": 0,
      "type": 0
    },
    "StaticControl26": {
      "shape": 2,
      "x": 224,
      "y": 296,
      "angle": 181,
      "size": 0,
      "type": 0
    },
    "StaticControl27": {
      "shape": 2,
      "x": 232,
      "y": 324,
      "angle": 213,
      "size": 0,
      "type": 0
    },
    "StaticControl28": {
      "shape": 2,
      "x": 152,
      "y": 276,
      "angle": 90,
      "size": 0,
      "type": 0
    },
    "StaticControl29": {
      "shape": 2,
      "x": 132,
      "y": 292,
      "angle": 59,
      "size": 0,
      "type": 0
    }
  }
}
