{
  "header": {
    "save_format": 1,
    "name": "GIORGIO",
    "author": "",
    "level": 5,
    "hole": 6,
    "par": 3,
    "foreground": 18,
    "background": 0,
    "special": 0,
    "height": 530,
    "snap": 4,
    "n_static": 33,
    "n_elliptic": 0,
    "n_linear": 0
  },
  "body": {
    "StaticControl1": {
      "shape": 2,
      "x": 172,
      "y": 176,
      "angle": 0,
      "size": 0,
      "type": 0
    },
    "StaticControl2": {
      "shape": 2,
      "x": 260,
      "y": 232,
      "angle": 0,
      "size": 0,
      "type": 0
    },
    "StaticControl3": {
      "shape": 2,
      "x": 80,
      "y": 224,
      "angle": 0,
      "size": 0,
      "type": 0
    },
    "StaticControl4": {
      "shape": 2,
      "x": 40,
      "y": 240,
      "angle": 0,
      "size": 0,
      "type": 0
    },
    "StaticControl5": {
      "shape": 2,
      "x": 124,
      "y": 44,
      "angle": 0,
      "size": 0,
      "type": 0
    },
    "StaticControl6": {
      "shape": 1,
      "x": 124,
      "y": 84,
      "angle": 0,
      "size": 0,
      "type": 0
    },
    "StaticControl7": {
      "shape": 1,
      "x": 124,
      "y": 128,
      "angle": 0,
      "size": 1,
      "type": 1
    },
    "StaticControl8": {
      "shape": 1,
      "x": 124,
      "y": 176,
      "angle": 0,
      "size": 1,
      "type": 1
    },
    "StaticControl9": {
      "shape": 1,
      "x": 124,
      "y": 224,
      "angle": 0,
      "size": 1,
      "type": 1
    },
    "StaticControl10": {
      "shape": 0,
      "x": 180,
      "y": 208,
      "angle": 97,
      "size": 0,
      "type": 0
    },
    "StaticControl11": {
      "shape": 1,
      "x": 216,
      "y": 224,
      "angle": -21,
      "size": 0,
      "type": 2
    },
    "StaticControl12": {
      "shape": 0,
      "x": 308,
      "y": 272,
      "angle": 14,
      "size": 0,
      "type": 0
    },
    "StaticControl13": {
      "shape": 0,
      "x": 344,
      "y": 292,
      "angle": 77,
      "size": 0,
      "type": 0
    },
    "StaticControl14": {
      "shape": 1,
      "x": 132,
      "y": 360,
      "angle": 0,
      "size": 1,
      "type": 1
    },
    "StaticControl15": {
      "shape": 1,
      "x": 132,
      "y": 400,
      "angle": 0,
      "size": 1,
      "type": 1
    },
    "StaticControl16": {
      "shape": 1,
      "x": 132,
      "y": 444,
      "angle": 0,
      "size": 1,
      "type": 1
    },
    "StaticControl17": {
      "shape": 1,
      "x": 132,
      "y": 496,
      "angle": 0,
      "size": 1,
      "type": 1
    },
    "StaticControl18": {
      "shape": 0,
      "x": 196,
      "y": 492,
      "angle": 14,
      "size": 0,
      "type": 0
    },
    "StaticControl19": {
      "shape": 0,
      "x": 288,
      "y": 508,
      "angle": -9,
      "size": 0,
      "type": 0
    },
    "StaticControl20": {
      "shape": 0,
      "x": 360,
      "y": 508,
      "angle": 5,
      "size": 0,
      "type": 0
    },
    "StaticControl21": {
      "shape": 0,
      "x": 208,
      "y": 420,
      "angle": -9,
      "size": 0,
      "type": 0
    },
    "StaticControl22": {
      "shape": 0,
      "x": 292,
      "y": 456,
      "angle": 2,
      "size": 0,
      "type": 0
    },
    "StaticControl23": {
      "shape": 0,
      "x": 360,
      "y": 416,
      "angle": 10,
      "size": 0,
      "type": 0
    },
    "StaticControl24": {
      "shape": 0,
      "x": 292,
      "y": 372,
      "angle": -2,
      "size": 0,
      "type": 0
    },
    "StaticControl25": {
      "shape": 0,
      "x": 200,
      "y": 348,
      "angle": -5,
      "size": 0,
      "type": 0
    },
    "StaticControl26": {
      "shape": 0,
      "x": 368,
      "y": 352,
      "angle": 3,
      "size": 0,
      "type": 0
    },
    "StaticControl27": {
      "shape": 0,
      "x": 36,
      "y": 372,
      "angle": 9,
      "size": 0,
      "type": 0
    },
    "StaticControl28": {
      "shape": 0,
      "x": 80,
      "y": 420,
      "angle": -8,
      "size": 0,
      "type": 0
    },
    "StaticControl29": {
      "shape": 0,
      "x": 48,
      "y": 484,
      "angle": 9,
      "size": 0,
      "type": 0
    },
    "StaticControl30": {
      "shape": 1,
      "x": 68,
      "y": 284,
      "angle": 0,
      "size": 2,
      "type": 1
    },
    "StaticControl31": {
      "shape": 1,
      "x": 136,
      "y": 296,
      "angle": 0,
      "size": 2,
      "type": 1
    },
    "StaticControl32": {
      "shape": 1,
      "x": 196,
      "y": 272,
      "angle": 0,
      "size": 2,
      "type": 1
    },
    "StaticControl33": {
      "shape": 1,
      "x": 256,
      "y": 292,
      "angle": 0,
      "size": 2,
      "type": 1
    }
  }
}
